snipeit_api/Accessories.py
snipeit_api/Assets.py
snipeit_api/Company.py
snipeit_api/Components.py
snipeit_api/Consumables.py
snipeit_api/Locations.py
snipeit_api/Models.py
snipeit_api/StatusLabels.py
snipeit_api/Users.py
snipeit_api/__init__.py
snipeit_api-0.1.dist-info/METADATA
snipeit_api-0.1.dist-info/RECORD
snipeit_api-0.1.dist-info/WHEEL
snipeit_api-0.1.dist-info/top_level.txt
